todorant_tui/__init__.py
todorant_tui/__main__.py
todorant_tui/app.py
todorant_tui/components/__init__.py
todorant_tui/components/bool_input.py
todorant_tui/components/current_task.py
todorant_tui/components/date_input.py
todorant_tui/components/progress.py
todorant_tui/components/text_input.py
todorant_tui/components/todo_list.py
todorant_tui/components/year_month_input.py
todorant_tui/config.py
todorant_tui/models.py
todorant_tui/todorant_client.py
todorant_tui/views/__init__.py
todorant_tui/views/create_todo.py
todorant_tui/views/current.py
todorant_tui/views/edit_todo.py
todorant_tui/views/planning.py
todorant_tui-0.1.0.dist-info/LICENSE
todorant_tui-0.1.0.dist-info/WHEEL
todorant_tui-0.1.0.dist-info/METADATA
todorant_tui-0.1.0.dist-info/RECORD
