Metadata-Version: 2.1
Name: todorant-tui
Version: 0.1.0
Summary: 
Author: Artyom Chebotaryov
Author-email: ideriki@gmail.com
Requires-Python: >=3.8,<4.0
Classifier: Programming Language :: Python :: 3
Classifier: Programming Language :: Python :: 3.10
Classifier: Programming Language :: Python :: 3.8
Classifier: Programming Language :: Python :: 3.9
Requires-Dist: httpx (>=0.23.0,<0.24.0)
Requires-Dist: pydantic[dotenv] (>=1.9.1,<2.0.0)
Requires-Dist: textual (>=0.1.18,<0.2.0)
Requires-Dist: textual-inputs (>=0.2.6,<0.3.0)
